{
  "js-file":[
    {
      "file":"./dist/animation/index",
      "name":"animation",
      "export-kind":"named export",
      "entry-point":[
        "requestAnimationHandler"
      ]
    },
    {
      "file":"./dist/api/index",
      "name":"api",
      "export-kind":"named export",
      "entry-point":[
        "fetchAPI"
      ]
    },
    {
      "file":"./dist/css/index",
      "name":"css",
      "export-kind":"named export",
      "entry-point":[
        "cx",
        "numberToPx",
        "pxToNumber",
        "hexToRgba"
      ]
    },
    {
      "file":"./dist/date/index",
      "name":"date",
      "export-kind":"named export",
      "entry-point":[
        "formatTimeUnit",
        "convertStringToDate",
        "convertDateToString",
        "convertEpochToDate",
        "convertDateToEpoch",
        "setToMidnight",
        "setToEndOfDay",
        "setToFirstDayOfMonth"
      ]
    },
    {
      "file":"./dist/emitter/index",
      "name":"emitter",
      "export-kind":"named export",
      "entry-point":[
        {
          "type":"interface",
          "name":"Handler"
        },
        {
          "type":"interface",
          "name":"WildcardHandler"
        },
        {
          "type":"interface",
          "name":"EventHandlerList"
        },
        {
          "type":"interface",
          "name":"WildCardEventHandlerList"
        },
        {
          "type":"interface",
          "name":"EventHandlerMap"
        },
        {
          "type":"interface",
          "name":"Emitter"
        },
        "mitt"
      ]
    },
    {
      "file":"./dist/error/index",
      "name":"error",
      "export-kind":"named export",
      "entry-point":[
        "CashboundError",
        "UnauthorizedError",
        "TimeoutError",
        "castingError",
        "throwError"
      ]
    },
    {
      "file":"./dist/image/index",
      "name":"image",
      "export-kind":"named export",
      "entry-point":[
        "prefetchImageFromURL",
        "convertImageToBase64"
      ]
    },
    {
      "file":"./dist/misc/index",
      "name":"misc",
      "export-kind":"named export",
      "entry-point":[
        "noop",
        "delay",
        "copyToClipboard",
        "debounce",
        "throttle",
        "toIDR",
        "redirectNative",
        "openToNewTabNative"
      ]
    },
    {
      "file":"./dist/observer/index",
      "name":"observer",
      "export-kind":"named export",
      "entry-point":[
        {
          "type":"interface",
          "name":"ResizeObserverFnType"
        },
        {
          "type":"interface",
          "name":"ResizerObserverStateType"
        },
        "resizeObserverHandler",
        {
          "type":"interface",
          "name":"IntersectObserverFnType"
        },
        {
          "type":"interface",
          "name":"IntersectObserverStateType"
        },
        "intersectObserverHandler"
      ]
    },
    {
      "file":"./dist/parse/index",
      "name":"parse",
      "export-kind":"named export",
      "entry-point":[
        "safeParseToString",
        "safeParseToNumber",
        "safeParseJSON",
        "safeStringifyJSON",
        "safeParseBoolean"
      ]
    },
    {
      "file":"./dist/phone/index",
      "name":"phone",
      "export-kind":"named export",
      "entry-point":[
        "formattingPhoneNumber",
        "sanitizePhoneNumber"
      ]
    },
    {
      "file":"./dist/process/index",
      "name":"process",
      "export-kind":"named export",
      "entry-point":[
        "abortProcess",
        "createAbortSignal",
        "combineAbortSignal"
      ]
    },
    {
      "file":"./dist/url/index",
      "name":"url",
      "export-kind":"named export",
      "entry-point":[
        "buildURLQueryParameters",
        "constructURL",
        "parseURL"
      ]
    }
  ],
  "static-file":[],
  "custom-config":[]
}